crawler_user_agents-1.27.0.dist-info/licenses/LICENSE
crawleruseragents/__init__.py
crawleruseragents/composer.json
crawleruseragents/crawler-user-agents.json
crawleruseragents/package-lock.json
crawleruseragents/package.json
crawleruseragents/test_harness.py
crawleruseragents/test_validation.py
crawleruseragents/validate.py
crawler_user_agents-1.27.0.dist-info/METADATA
crawler_user_agents-1.27.0.dist-info/WHEEL
crawler_user_agents-1.27.0.dist-info/top_level.txt
crawler_user_agents-1.27.0.dist-info/RECORD
