Metadata-Version: 2.4
Name: crawler-user-agents
Version: 1.27.0
Summary: Syntactic patterns of HTTP user-agents used by bots / robots / crawlers / scrapers / spiders.
Author-email: Martin Monperrus <martin.monperrus@gnieh.org>
Project-URL: Homepage, https://github.com/monperrus/crawler-user-agents
License-File: LICENSE
Provides-Extra: dev
Requires-Dist: attrs==23.2.0; extra == "dev"
Requires-Dist: iniconfig==2.0.0; extra == "dev"
Requires-Dist: jsonschema==4.22.0; extra == "dev"
Requires-Dist: jsonschema-specifications==2023.12.1; extra == "dev"
Requires-Dist: packaging==24.0; extra == "dev"
Requires-Dist: pluggy==1.5.0; extra == "dev"
Requires-Dist: pytest==8.2.0; extra == "dev"
Requires-Dist: referencing==0.35.0; extra == "dev"
Requires-Dist: rpds-py==0.18.0; extra == "dev"
Dynamic: license-file
